fluidon_doepy/__init__.py
fluidon_doepy/build.py
fluidon_doepy/doe_functions.py
fluidon_doepy/pydoe_corrected.py
fluidon_doepy/read_write.py
fluidon_doepy/Data/params.csv
fluidon_doepy/Test/doe_test1.py
fluidon_doepy/Test/doepy/__init__.py
fluidon_doepy/Test/doepy/build.py
fluidon_doepy/Test/doepy/doe_functions.py
fluidon_doepy/Test/doepy/params.csv
fluidon_doepy/Test/doepy/pydoe_corrected.py
fluidon_doepy/Test/doepy/read_write.py
fluidon_doepy-0.0.7.dist-info/LICENSE
fluidon_doepy-0.0.7.dist-info/METADATA
fluidon_doepy-0.0.7.dist-info/WHEEL
fluidon_doepy-0.0.7.dist-info/top_level.txt
fluidon_doepy-0.0.7.dist-info/RECORD
